pykli/__init__.py
pykli/__main__.py
pykli/completer.py
pykli/keybindgings.py
pykli/ksqldb.py
pykli/repl_eval.py
pykli/repl_print.py
pykli/repl_read.py
pykli/tokens.py
pykli-1.1.4.dist-info/LICENSE
pykli-1.1.4.dist-info/METADATA
pykli-1.1.4.dist-info/WHEEL
pykli-1.1.4.dist-info/entry_points.txt
pykli-1.1.4.dist-info/RECORD
