Metadata-Version: 2.1
Name: pykli
Version: 1.1.4
Summary: Interactive ksqlDB command line client with autocompletion and syntax highlighting
Home-page: https://github.com/eshepelyuk/pykli
License: MIT
Keywords: cli,kafka,tui,confluent,ksql,ksqldb
Author: Ievgenii Shepeliuk
Author-email: eshepelyuk@gmail.com
Requires-Python: >=3.10,<4.0
Classifier: License :: OSI Approved :: MIT License
Classifier: Programming Language :: Python :: 3
Classifier: Programming Language :: Python :: 3.10
Classifier: Programming Language :: Python :: 3.11
Requires-Dist: cli_helpers[styles] (>=2.3.0,<3.0.0)
Requires-Dist: click (>=8.1.3,<9.0.0)
Requires-Dist: httpx[http2] (>=0.24.1,<0.25.0)
Requires-Dist: prompt-toolkit (>=3.0.38,<4.0.0)
Requires-Dist: pygments (>=2.15.1,<3.0.0)
Requires-Dist: sqlparse (>=0.4.4,<0.5.0)
Requires-Dist: xdg-base-dirs (>=6.0.0,<7.0.0)
Project-URL: Repository, https://github.com/eshepelyuk/pykli
